{"nodes": [{"id": "home_dbechstein_projekte_voip_src_core_sdk_iceoptions_cs", "label": "IceOptions.cs", "file_type": "code", "source_file": "src/Core/Sdk/IceOptions.cs", "source_location": "L1"}, {"id": "csharp_namespace:45f53ea1e016eaaa", "label": "CalloraVoipSdk", "file_type": "code", "source_file": "src/Core/Sdk/IceOptions.cs", "source_location": "L1", "type": "namespace", "metadata": {"kind": "csharp_namespace", "namespace": "CalloraVoipSdk"}}, {"id": "home_dbechstein_projekte_voip_src_core_sdk_iceoptions_calloravoipsdk_iceoptions", "label": "IceOptions", "file_type": "code", "source_file": "src/Core/Sdk/IceOptions.cs", "source_location": "L6", "metadata": {"namespace": "CalloraVoipSdk", "scope_chain": ["s0"]}, "_callable": true}, {"id": "list", "label": "List", "file_type": "code", "source_file": "", "source_location": "", "origin_file": "/home/dbechstein/Projekte/voip/src/Core/Sdk/IceOptions.cs"}, {"id": "iceserverconfiguration", "label": "IceServerConfiguration", "file_type": "code", "source_file": "", "source_location": "", "origin_file": "/home/dbechstein/Projekte/voip/src/Core/Sdk/IceOptions.cs"}, {"id": "timespan", "label": "TimeSpan", "file_type": "code", "source_file": "", "source_location": "", "origin_file": "/home/dbechstein/Projekte/voip/src/Core/Sdk/IceOptions.cs"}, {"id": "home_dbechstein_projekte_voip_src_core_sdk_iceoptions_calloravoipsdk_iceoptions_toconfiguration", "label": ".ToConfiguration()", "file_type": "code", "source_file": "src/Core/Sdk/IceOptions.cs", "source_location": "L28", "metadata": {"namespace": "CalloraVoipSdk", "scope_chain": ["s0"]}, "_callable": true}, {"id": "iceconfiguration", "label": "IceConfiguration", "file_type": "code", "source_file": "", "source_location": "", "origin_file": "/home/dbechstein/Projekte/voip/src/Core/Sdk/IceOptions.cs"}], "edges": [{"source": "home_dbechstein_projekte_voip_src_core_sdk_iceoptions_cs", "target": "csharp_namespace:45f53ea1e016eaaa", "relation": "contains", "confidence": "EXTRACTED", "source_file": "src/Core/Sdk/IceOptions.cs", "source_location": "L1", "weight": 1.0}, {"source": "home_dbechstein_projekte_voip_src_core_sdk_iceoptions_cs", "target": "home_dbechstein_projekte_voip_src_core_sdk_iceoptions_calloravoipsdk_iceoptions", "relation": "contains", "confidence": "EXTRACTED", "source_file": "src/Core/Sdk/IceOptions.cs", "source_location": "L6", "weight": 1.0}, {"source": "home_dbechstein_projekte_voip_src_core_sdk_iceoptions_calloravoipsdk_iceoptions", "target": "list", "relation": "references", "confidence": "EXTRACTED", "source_file": "src/Core/Sdk/IceOptions.cs", "source_location": "L16", "weight": 1.0, "context": "field", "metadata": {"ref_token": "List"}}, {"source": "home_dbechstein_projekte_voip_src_core_sdk_iceoptions_calloravoipsdk_iceoptions", "target": "iceserverconfiguration", "relation": "references", "confidence": "EXTRACTED", "source_file": "src/Core/Sdk/IceOptions.cs", "source_location": "L16", "weight": 1.0, "context": "generic_arg", "metadata": {"ref_token": "IceServerConfiguration"}}, {"source": "home_dbechstein_projekte_voip_src_core_sdk_iceoptions_calloravoipsdk_iceoptions", "target": "timespan", "relation": "references", "confidence": "EXTRACTED", "source_file": "src/Core/Sdk/IceOptions.cs", "source_location": "L21", "weight": 1.0, "context": "field", "metadata": {"ref_token": "TimeSpan"}}, {"source": "home_dbechstein_projekte_voip_src_core_sdk_iceoptions_calloravoipsdk_iceoptions", "target": "home_dbechstein_projekte_voip_src_core_sdk_iceoptions_calloravoipsdk_iceoptions_toconfiguration", "relation": "method", "confidence": "EXTRACTED", "source_file": "src/Core/Sdk/IceOptions.cs", "source_location": "L28", "weight": 1.0}, {"source": "home_dbechstein_projekte_voip_src_core_sdk_iceoptions_calloravoipsdk_iceoptions_toconfiguration", "target": "iceconfiguration", "relation": "references", "confidence": "EXTRACTED", "source_file": "src/Core/Sdk/IceOptions.cs", "source_location": "L28", "weight": 1.0, "context": "return_type", "metadata": {"ref_token": "IceConfiguration"}}], "raw_calls": [], "csharp_type_table": {"path": "/home/dbechstein/Projekte/voip/src/Core/Sdk/IceOptions.cs", "table": {"ConnectivityCheckTimeout": "TimeSpan", "Servers": "List"}}}